CHANGES.rst
LICENSE.txt
MANIFEST.in
README.rst
setup.py
Gribble.egg-info/PKG-INFO
Gribble.egg-info/SOURCES.txt
Gribble.egg-info/dependency_links.txt
Gribble.egg-info/requires.txt
Gribble.egg-info/top_level.txt
bin/gribble
contrib/gribble-bash.sh
contrib/gribble-el6-init.d
contrib/gribble-init.d
contrib/gribble-supervisor.conf
contrib/gribble-upstart.conf
gribble/__init__.py
gribble/base_log.py
gribble/config.py
gribble/glob_safe_config_parser.py
gribble/pidfile.py
gribble/run_queue.py
gribble/ssh_tunnel.py
gribble/unicode_dammit.py
gribble/utils.py
gribble/dispatcher/__init__.py
gribble/dispatcher/tail.py
gribble/dispatcher/worker.py
gribble/tests/__init__.py
gribble/tests/fixtures.py
gribble/tests/service.py
gribble/tests/test_glob_sections.py
gribble/tests/test_kafka_transport.py
gribble/tests/test_transport_config.py
gribble/tests/test_zmq_transport.py
gribble/transports/__init__.py
gribble/transports/base_transport.py
gribble/transports/exception.py
gribble/transports/http_transport.py
gribble/transports/kafka_transport.py
gribble/transports/kinesis_transport.py
gribble/transports/mqtt_transport.py
gribble/transports/rabbitmq_transport.py
gribble/transports/redis_transport.py
gribble/transports/sns_transport.py
gribble/transports/sqs_transport.py
gribble/transports/stdout_transport.py
gribble/transports/stomp_transport.py
gribble/transports/tcp_transport.py
gribble/transports/udp_transport.py
gribble/transports/zmq_transport.py
gribble/worker/__init__.py
gribble/worker/tail.py
gribble/worker/tail_manager.py
gribble/worker/worker.py
requirements/base.txt
requirements/base26.txt
requirements/tests.txt
requirements/zeromq.txt