Metadata-Version: 1.1
Name: Gribble
Version: 1.0.0
Summary: python daemon that munches on logs and sends their contents to logstash
Home-page: http://github.com/JamieCressey/gribble
Author: Jamie Cressey
Author-email: UNKNOWN
License: LICENSE.txt
Platform: UNKNOWN
Classifier: Development Status :: 5 - Production/Stable
Classifier: Intended Audience :: System Administrators
Classifier: License :: OSI Approved :: MIT License
Classifier: Programming Language :: Python :: 2.6
Classifier: Programming Language :: Python :: 2.7
Classifier: Topic :: System :: Logging
Requires: six
